georapid/__int__.py
georapid/client.py
georapid/conflicts.py
georapid/factory.py
georapid/fires.py
georapid/formats.py
georapid/geodetic.py
georapid/geojson.py
georapid/joins.py
georapid/protests.py
georapid/units.py
georapid-0.2.dist-info/LICENSE
georapid-0.2.dist-info/METADATA
georapid-0.2.dist-info/WHEEL
georapid-0.2.dist-info/top_level.txt
georapid-0.2.dist-info/RECORD
