Metadata-Version: 2.1
Name: georapid
Version: 0.2
Summary: Query broadcasted news/events worldwide and visualize them using spatial aggregations.
Home-page: https://github.com/Geospatial-AI-DE/georapid-py
Author: Jan Tschada
Author-email: gisfromscratch@live.de
Project-URL: Homepage, https://geospatial-ai.de
Project-URL: GitHub, https://github.com/Geospatial-AI-DE/georapid-py
Project-URL: Documentation, https://georapid.readthedocs.io/en/latest
Keywords: geospatial,intelligence,news
Classifier: Programming Language :: Python :: 3
Classifier: License :: OSI Approved :: Apache Software License
Classifier: Operating System :: OS Independent
Requires-Python: >=3.7
License-File: LICENSE
Requires-Dist: requests
